Quorum/__init__.py
Quorum/apis/__init__.py
Quorum/apis/block_explorers/__init__.py
Quorum/apis/block_explorers/chains_api.py
Quorum/apis/block_explorers/source_code.py
Quorum/apis/git_api/__init__.py
Quorum/apis/git_api/git_manager.py
Quorum/apis/governance/__init__.py
Quorum/apis/governance/aave_governance.py
Quorum/apis/governance/data_models.py
Quorum/apis/price_feeds/__init__.py
Quorum/apis/price_feeds/chainlink_api.py
Quorum/apis/price_feeds/chronicle_api.py
Quorum/apis/price_feeds/coingecko_api.py
Quorum/apis/price_feeds/price_feed_utils.py
Quorum/auto_report/AaveReportTemplate.md.j2
Quorum/auto_report/__init__.py
Quorum/auto_report/aave_tags.py
Quorum/checks/__init__.py
Quorum/checks/check.py
Quorum/checks/diff.py
Quorum/checks/global_variables.py
Quorum/checks/new_listing.py
Quorum/checks/price_feed.py
Quorum/checks/proposal_check.py
Quorum/checks/review_diff.py
Quorum/entry_points/__init__.py
Quorum/entry_points/cli_arguments.py
Quorum/entry_points/quorum_cli.py
Quorum/entry_points/implementations/__init__.py
Quorum/entry_points/implementations/check_proposal.py
Quorum/entry_points/implementations/check_proposal_config.py
Quorum/entry_points/implementations/check_proposal_id.py
Quorum/entry_points/implementations/create_report.py
Quorum/entry_points/implementations/ipfs_validator.py
Quorum/entry_points/implementations/setup_quorum.py
Quorum/llm/__init__.py
Quorum/llm/jinja_utils.py
Quorum/llm/chains/__init__.py
Quorum/llm/chains/cached_llm.py
Quorum/llm/chains/first_deposit_chain.py
Quorum/llm/chains/ipfs_validation_chain.py
Quorum/llm/prompts/__init__.py
Quorum/llm/prompts/first_deposit_prompt.j2
Quorum/llm/prompts/ipfs_validation_prompt_part1.j2
Quorum/llm/prompts/ipfs_validation_prompt_part2.j2
Quorum/templates/.env.example
Quorum/templates/README.md
Quorum/templates/__init__.py
Quorum/templates/execution.json
Quorum/templates/ground_truth.json
Quorum/tests/__init__.py
Quorum/tests/blockchain_api_test.py
Quorum/tests/conftest.py
certora_quorum-20250108.130548.490490.dist-info/LICENSE
certora_quorum-20250108.130548.490490.dist-info/METADATA
certora_quorum-20250108.130548.490490.dist-info/WHEEL
certora_quorum-20250108.130548.490490.dist-info/entry_points.txt
certora_quorum-20250108.130548.490490.dist-info/top_level.txt
certora_quorum-20250108.130548.490490.dist-info/RECORD
