Metadata-Version: 2.1
Name: certora-quorum
Version: 20250108.130548.490490
Summary: Quorum: A tool for managing proposals and reports
Author-email: Niv Vaknin <niv@certora.com>, Liav Katry <liav@certora.com>
License: MIT License
Project-URL: Homepage, https://github.com/Certora/Quorum
Project-URL: Source, https://github.com/Certora/Quorum
Keywords: Quorum,Proposals,Reports
Classifier: Programming Language :: Python :: 3
Classifier: License :: OSI Approved :: MIT License
Classifier: Operating System :: OS Independent
License-File: LICENSE
Requires-Dist: requests
Requires-Dist: GitPython
Requires-Dist: py-solc-x
Requires-Dist: pydantic
Requires-Dist: eth-abi
Requires-Dist: eth-utils
Requires-Dist: pytest
Requires-Dist: eth-hash[pycryptodome]
Requires-Dist: langchain
Requires-Dist: jinja2
Requires-Dist: langchain-anthropic
Requires-Dist: langgraph
Requires-Dist: langchain_community
Requires-Dist: python-dotenv
Requires-Dist: json5
Requires-Dist: argcomplete
